robots/__init__.py
robots/__main__.py
robots/parser.py
robots/robotparser.py
robotspy-0.12.0.dist-info/LICENSE.md
robotspy-0.12.0.dist-info/METADATA
robotspy-0.12.0.dist-info/WHEEL
robotspy-0.12.0.dist-info/entry_points.txt
robotspy-0.12.0.dist-info/top_level.txt
robotspy-0.12.0.dist-info/RECORD
