Metadata-Version: 2.1
Name: robotspy
Version: 0.12.0
Summary: Robots Exclusion Protocol File Parser
Home-page: https://github.com/andreburgaud/robotspy
Author: Andre Burgaud
Author-email: andre.burgaud@gmail.com
License: MIT
Classifier: License :: OSI Approved :: MIT License
Classifier: Programming Language :: Python :: 3
Classifier: Programming Language :: Python :: 3.8
Classifier: Programming Language :: Python :: 3.9
Classifier: Programming Language :: Python :: 3.10
Classifier: Programming Language :: Python :: 3.11
Classifier: Programming Language :: Python :: 3.12
License-File: LICENSE.md
